{"cameraMode":{"drawMode":0,"name":"Shaded","section":"Shading Mode"},"sceneLighting":false,"audioPlay":false,"sceneViewState":{"showFog":true,"showMaterialUpdate":false,"showSkybox":false,"showFlares":true,"showImageEffects":true,"showParticleSystems":true},"in2DMode":false,"pivot":{"x":-378.70001220703127,"y":-53.5,"z":-226.3000030517578},"rotation":{"x":-0.22335363924503327,"y":-0.6920242309570313,"z":0.6431241631507874,"w":-0.24024106562137605},"size":22.501142501831056,"orthographic":false}